{"EntityFrameworkEvent":{"Database":"AuctionDb","ConnectionId":"971d985a-5905-44a8-b4be-94d0b84c72ce","ContextId":"8ee5f593-c5a8-45d3-a770-6537ea38bd0b:0","Entries":[{"Table":"PlayerRegister","Name":"PlayerRegister","PrimaryKey":{"PlayerRegisterId":"ab2093e9-6eeb-4cf7-9ae0-3b36f9fb6a9f"},"Action":"Insert","ColumnValues":{"PlayerRegisterId":"ab2093e9-6eeb-4cf7-9ae0-3b36f9fb6a9f","AlternativePhoneNo":"string","BasePrice":null,"Batsmen":true,"BattingAllRounder":true,"Bowler":true,"BowlingAllRounder":true,"CreatedBy":null,"CreatedOn":"2023-12-27T09:09:32.6391748Z","DOB":"2023-12-27T09:08:17.841Z","Email":"string","FirstName":"string","Gender":"string","IsActive":true,"IsDeleted":false,"LastName":"string","LastPlayedYear":"2023-12-27T09:08:17.841Z","MobileNo":"string","Password":"2757cb3cafc39af451abb2697be79b4ab61d63d74d85b0418629de8c26811b529f3f3780d0150063ff55a2beee74c4ec102a2a2731a1f1f7f10d473ad18a6a87","PreviousTeamId":null,"ProfilePicture":"string","UpdatedBy":null,"UpdatedOn":null,"WicketKeeper":true,"WinningBid":null},"Valid":true}],"Result":1,"Success":true},"EventType":"ReadWriteApplicationDbContext","Environment":{"UserName":"nisha","MachineName":"DCS03","DomainName":"DCS03","CallingMethodName":"System.Runtime.CompilerServices.AsyncMethodBuilderCore.Start()","AssemblyName":"System.Private.CoreLib, Version=6.0.0.0, Culture=neutral, PublicKeyToken=7cec85d7bea7798e","Culture":"en-IN"},"StartDate":"2023-12-27T09:09:32.7314208Z","EndDate":"2023-12-27T09:09:32.7703689Z","Duration":39}